{
    "rounds": [
        {
            "round": 1,
            "button_id": 8,
            "button_name": "Button 8",
            "button_x": 1730,
            "button_y": 720,
            "click_x": 1910,
            "click_y": 600,
            "hit": false,
            "timestamp": 5.797321557998657
        },
        {
            "round": 2,
            "button_id": 2,
            "button_name": "Button 2",
            "button_x": 1130,
            "button_y": 420,
            "click_x": 1330,
            "click_y": 220,
            "hit": false,
            "timestamp": 12.22778034210205
        },
        {
            "round": 3,
            "button_id": 7,
            "button_name": "Button 7",
            "button_x": 1430,
            "button_y": 720,
            "click_x": 1590,
            "click_y": 560,
            "hit": false,
            "timestamp": 16.318669319152832
        },
        {
            "round": 4,
            "button_id": 1,
            "button_name": "Button 1",
            "button_x": 830,
            "button_y": 420,
            "click_x": 730,
            "click_y": 320,
            "hit": false,
            "timestamp": 21.226234912872314
        },
        {
            "round": 5,
            "button_id": 9,
            "button_name": "Button 9",
            "button_x": 830,
            "button_y": 1020,
            "click_x": 940,
            "click_y": 1120,
            "hit": false,
            "timestamp": 29.654666423797607
        },
        {
            "round": 6,
            "button_id": 10,
            "button_name": "Button 10",
            "button_x": 1130,
            "button_y": 1020,
            "click_x": 1170,
            "click_y": 1020,
            "hit": false,
            "timestamp": 33.037392139434814
        },
        {
            "round": 7,
            "button_id": 6,
            "button_name": "Button 6",
            "button_x": 1130,
            "button_y": 720,
            "click_x": 1260,
            "click_y": 720,
            "hit": false,
            "timestamp": 38.00325655937195
        },
        {
            "round": 8,
            "button_id": 11,
            "button_name": "Button 11",
            "button_x": 1430,
            "button_y": 1020,
            "click_x": 1530,
            "click_y": 1020,
            "hit": false,
            "timestamp": 42.544854402542114
        },
        {
            "round": 9,
            "button_id": 5,
            "button_name": "Button 5",
            "button_x": 830,
            "button_y": 720,
            "click_x": 770,
            "click_y": 780,
            "hit": false,
            "timestamp": 48.06870102882385
        },
        {
            "round": 10,
            "button_id": 4,
            "button_name": "Button 4",
            "button_x": 1730,
            "button_y": 420,
            "click_x": 1810,
            "click_y": 420,
            "hit": false,
            "timestamp": 53.75618767738342
        },
        {
            "round": 11,
            "button_id": 3,
            "button_name": "Button 3",
            "button_x": 1430,
            "button_y": 420,
            "click_x": 1500,
            "click_y": 420,
            "hit": false,
            "timestamp": 57.655168294906616
        },
        {
            "round": 12,
            "button_id": 12,
            "button_name": "Button 12",
            "button_x": 1730,
            "button_y": 1020,
            "click_x": 1790,
            "click_y": 1020,
            "hit": false,
            "timestamp": 64.77505445480347
        }
    ]
} 